{
  "Users": {
    "001": {
      "Name": "Mohamed Sheikh",
      "Subscription": "Basic Plan",
      "Status": {
        "Online": {
          "Streams": {
            "activeStreams": 3,
            "watching": ["stream_2", "stream_3", "stream_9"]
          }
        },
        "offline": { "lastOnline": null }
      }
    },
    "002": {
      "Name": "David Beckham",
      "Subscription": "Medium Plan",
      "Status": {
        "Online": {
          "Streams": {
            "activeStreams": 2,
            "watching": ["stream_2", "stream_4"]
          }
        },
        "offline": { "lastOnline": null }
      }
    }
  }
}
